[
  {
    "time": "07:47:31",
    "company": "Tesla",
    "price": 428.32,
    "change": -0.01234,
    "shift": "\ud83d\udd3b Negative Shift"
  },
  {
    "time": "07:47:31",
    "company": "Apple",
    "price": 293.28,
    "change": -0.03643,
    "shift": "\ud83d\udd3b Negative Shift"
  },
  {
    "time": "07:47:31",
    "company": "Google",
    "price": 400.81,
    "change": 0.02642,
    "shift": "\ud83d\ude80 Positive Shift"
  },
  {
    "time": "07:47:32",
    "company": "Amazon",
    "price": 272.68,
    "change": 0.00884,
    "shift": "\ud83d\ude80 Positive Shift"
  },
  {
    "time": "07:47:32",
    "company": "Microsoft",
    "price": 415.15,
    "change": 0.0047,
    "shift": "\ud83d\ude80 Positive Shift"
  }
]